saysomething/__init__.py
saysomething/__main__.py
saysomething/data.py
saysomething/display.py
say_something_moon-1.0.0.dist-info/METADATA
say_something_moon-1.0.0.dist-info/WHEEL
say_something_moon-1.0.0.dist-info/entry_points.txt
say_something_moon-1.0.0.dist-info/top_level.txt
say_something_moon-1.0.0.dist-info/RECORD
