Metadata-Version: 2.1
Name: say-something-moon
Version: 1.0.0
Summary: the chatbot when you are alone
Home-page: https://www.linkedin.com/in/moonyuema/
Author: Moon Ma
Author-email: moon30biology@gmail.com
License: MIT
Platform: UNKNOWN
Classifier: License :: OSI Approved :: MIT License
Classifier: Programming Language :: Python :: 3
Requires-Dist: typing
